MANIFEST.in
README.txt
setup.cfg
setup.py
docs/HISTORY.txt
horae/__init__.py
horae.workflow.egg-info/PKG-INFO
horae.workflow.egg-info/SOURCES.txt
horae.workflow.egg-info/dependency_links.txt
horae.workflow.egg-info/entry_points.txt
horae.workflow.egg-info/namespace_packages.txt
horae.workflow.egg-info/not-zip-safe
horae.workflow.egg-info/requires.txt
horae.workflow.egg-info/top_level.txt
horae/workflow/__init__.py
horae/workflow/configure.zcml
horae/workflow/interfaces.py
horae/workflow/properties.py
horae/workflow/utils.py
horae/workflow/views.py
horae/workflow/vocabulary.py
horae/workflow/workflow.py
horae/workflow/locales/horae.workflow.pot
horae/workflow/locales/de/LC_MESSAGES/horae.workflow.mo
horae/workflow/locales/de/LC_MESSAGES/horae.workflow.po
horae/workflow/templates/workflow.cpt
horae/workflow/templates/workflows.cpt