Metadata-Version: 1.0
Name: horae.workflow
Version: 1.0a1
Summary: UNKNOWN
Home-page: UNKNOWN
Author: Simon Kaeser
Author-email: skaeser@gmail.com
License: GPL
Platform: UNKNOWN
Classifier: Programming Language :: Python
